{
    "Lambda": 500,
    "classifierLr": 0.001,
    "beta": 1,
    "w_norm": 0.0001,
    "w_lr": 0.001,
    "l_lr": 0.001,
    "b_lr": 0.0033,
    "greedytrain": true,
    "nConvLayers": 1,
    "Convolutions": {
        "GlobalParams": {
            "paddingmode": "reflect",
            "triangle": false,
            "whiten": true,
            "batchnorm": true,
            "inhibition": "Softmax",
            "padding": 2,
            "stride": 1
        },
        "Layers": {
            "Conv1": {
                "out_channel": 512,
                "kernel": 5,
                "stride": 1,
                "padding": 2
            }
        }
    },
    "PoolingBlock": {
        "GlobalParams": {
            "Pooling": true
        },
        "Layers": {
            "Conv1": {
                "Type": "Avg",
                "kernel": 4,
                "padding": 1,
                "stride": 2
            }
        }
    },
    "Classifier": {
        "type": "Gradient",
        "out_channel": 10
    },
    "Topdown": false,
    "Rho": 0.001,
    "Eta": 0.1
}